README.rst
setup.py
tickle/__init__.py
tickle/builtins.py
tickle/lambdas.py
tickle.egg-info/PKG-INFO
tickle.egg-info/SOURCES.txt
tickle.egg-info/dependency_links.txt
tickle.egg-info/top_level.txt